whistle/__init__.py
whistle/_version.py
whistle/errors.py
whistle/event.py
whistle/listeners.py
whistle/dispatchers/__init__.py
whistle/dispatchers/asynchronous.py
whistle/dispatchers/base.py
whistle/dispatchers/synchronous.py
whistle/typing/__init__.py
whistle/typing/dispatcher.py
whistle/typing/event.py
whistle/typing/listener.py
whistle-2.1.4.dist-info/METADATA
whistle-2.1.4.dist-info/WHEEL
whistle-2.1.4.dist-info/licenses/LICENSE
whistle-2.1.4.dist-info/RECORD
