Metadata-Version: 2.4
Name: whistle
Version: 2.1.4
Summary: Event dispatcher (see python-whistle.readthedocs.io).
Author-email: Romain Dorgueil <romain@makersquad.fr>
License:                                  Apache License
License-File: LICENSE
Requires-Python: >=3.10
